todo_or_die/__init__.py
todo_or_die/decorator.py
todo_or_die/decorator_tests.py
todo_or_die/exceptions.py
todo_or_die/main.py
todo_or_die/main_tests.py
todo_or_die-0.1.1.dist-info/LICENSE
todo_or_die-0.1.1.dist-info/METADATA
todo_or_die-0.1.1.dist-info/WHEEL
todo_or_die-0.1.1.dist-info/top_level.txt
todo_or_die-0.1.1.dist-info/RECORD
