Metadata-Version: 2.1
Name: todo-or-die
Version: 0.1.1
Summary: Never let your TODOs rot in your python code ever again
Home-page: https://github.com/achedeuzot/py-todo-or-die
Author: Klemen Sever
Author-email: klemen@achedeuzot.me
License: MIT
Platform: UNKNOWN
Classifier: License :: OSI Approved :: MIT License
Classifier: Programming Language :: Python :: 3
Classifier: Programming Language :: Python :: 3.7
Classifier: Operating System :: OS Independent
License-File: LICENSE
